{
  "range": {
    "from": 801,
    "to": 900
  },
  "totalPatches": 173,
  "recipesAffected": 79,
  "patchesPerRecipe": [
    {
      "recipeIndex": 802,
      "count": 1
    },
    {
      "recipeIndex": 803,
      "count": 5
    },
    {
      "recipeIndex": 804,
      "count": 3
    },
    {
      "recipeIndex": 805,
      "count": 1
    },
    {
      "recipeIndex": 806,
      "count": 4
    },
    {
      "recipeIndex": 808,
      "count": 1
    },
    {
      "recipeIndex": 809,
      "count": 2
    },
    {
      "recipeIndex": 810,
      "count": 3
    },
    {
      "recipeIndex": 811,
      "count": 2
    },
    {
      "recipeIndex": 812,
      "count": 6
    },
    {
      "recipeIndex": 813,
      "count": 4
    },
    {
      "recipeIndex": 815,
      "count": 3
    },
    {
      "recipeIndex": 817,
      "count": 1
    },
    {
      "recipeIndex": 818,
      "count": 3
    },
    {
      "recipeIndex": 821,
      "count": 2
    },
    {
      "recipeIndex": 824,
      "count": 3
    },
    {
      "recipeIndex": 825,
      "count": 2
    },
    {
      "recipeIndex": 826,
      "count": 1
    },
    {
      "recipeIndex": 827,
      "count": 2
    },
    {
      "recipeIndex": 828,
      "count": 1
    },
    {
      "recipeIndex": 830,
      "count": 3
    },
    {
      "recipeIndex": 831,
      "count": 2
    },
    {
      "recipeIndex": 832,
      "count": 1
    },
    {
      "recipeIndex": 833,
      "count": 2
    },
    {
      "recipeIndex": 834,
      "count": 4
    },
    {
      "recipeIndex": 835,
      "count": 2
    },
    {
      "recipeIndex": 836,
      "count": 1
    },
    {
      "recipeIndex": 838,
      "count": 2
    },
    {
      "recipeIndex": 839,
      "count": 3
    },
    {
      "recipeIndex": 840,
      "count": 2
    },
    {
      "recipeIndex": 842,
      "count": 2
    },
    {
      "recipeIndex": 843,
      "count": 3
    },
    {
      "recipeIndex": 844,
      "count": 1
    },
    {
      "recipeIndex": 845,
      "count": 1
    },
    {
      "recipeIndex": 846,
      "count": 1
    },
    {
      "recipeIndex": 847,
      "count": 1
    },
    {
      "recipeIndex": 848,
      "count": 1
    },
    {
      "recipeIndex": 849,
      "count": 3
    },
    {
      "recipeIndex": 850,
      "count": 4
    },
    {
      "recipeIndex": 851,
      "count": 1
    },
    {
      "recipeIndex": 852,
      "count": 1
    },
    {
      "recipeIndex": 854,
      "count": 2
    },
    {
      "recipeIndex": 857,
      "count": 2
    },
    {
      "recipeIndex": 858,
      "count": 6
    },
    {
      "recipeIndex": 859,
      "count": 1
    },
    {
      "recipeIndex": 861,
      "count": 3
    },
    {
      "recipeIndex": 862,
      "count": 1
    },
    {
      "recipeIndex": 863,
      "count": 1
    },
    {
      "recipeIndex": 864,
      "count": 2
    },
    {
      "recipeIndex": 865,
      "count": 4
    },
    {
      "recipeIndex": 866,
      "count": 1
    },
    {
      "recipeIndex": 867,
      "count": 4
    },
    {
      "recipeIndex": 868,
      "count": 2
    },
    {
      "recipeIndex": 869,
      "count": 4
    },
    {
      "recipeIndex": 870,
      "count": 1
    },
    {
      "recipeIndex": 871,
      "count": 2
    },
    {
      "recipeIndex": 873,
      "count": 1
    },
    {
      "recipeIndex": 874,
      "count": 5
    },
    {
      "recipeIndex": 875,
      "count": 2
    },
    {
      "recipeIndex": 877,
      "count": 3
    },
    {
      "recipeIndex": 878,
      "count": 5
    },
    {
      "recipeIndex": 879,
      "count": 1
    },
    {
      "recipeIndex": 880,
      "count": 1
    },
    {
      "recipeIndex": 881,
      "count": 2
    },
    {
      "recipeIndex": 882,
      "count": 5
    },
    {
      "recipeIndex": 883,
      "count": 2
    },
    {
      "recipeIndex": 884,
      "count": 2
    },
    {
      "recipeIndex": 886,
      "count": 1
    },
    {
      "recipeIndex": 888,
      "count": 1
    },
    {
      "recipeIndex": 889,
      "count": 1
    },
    {
      "recipeIndex": 890,
      "count": 1
    },
    {
      "recipeIndex": 891,
      "count": 1
    },
    {
      "recipeIndex": 892,
      "count": 3
    },
    {
      "recipeIndex": 893,
      "count": 2
    },
    {
      "recipeIndex": 894,
      "count": 1
    },
    {
      "recipeIndex": 895,
      "count": 3
    },
    {
      "recipeIndex": 897,
      "count": 1
    },
    {
      "recipeIndex": 898,
      "count": 1
    },
    {
      "recipeIndex": 900,
      "count": 1
    }
  ],
  "reasonStats": {
    "Final QA EN↔VI: chuẩn hóa unit theo EN (thay 'đơn vị' khi suy ra chắc chắn); Final QA EN↔VI: sửa ingredientName dịch sai/literal theo EN": 168,
    "Final QA EN↔VI: chuẩn hóa unit theo EN (thay 'đơn vị' khi suy ra chắc chắn); Final QA EN↔VI: sửa ingredientName dịch sai/literal theo EN; Final QA EN↔VI: tinh chỉnh nghĩa theo ngữ cảnh EN gốc": 5
  },
  "files": {
    "en": "/home/dhpho/workspace/projects/chefmate-server/data/recipe-crawl-2026-03/recipes.json",
    "vi": "/home/dhpho/workspace/projects/chefmate-server/data/recipe-crawl-2026-03-vi/recipes.vi.json",
    "basePatch": "/home/dhpho/workspace/projects/chefmate-server/data/recipe-crawl-2026-03-vi/patches/patch_801_900.json",
    "finalPatch": "/home/dhpho/workspace/projects/chefmate-server/data/recipe-crawl-2026-03-vi/patches/final_patch_801_900.json"
  },
  "notes": "Final QA cực kỹ EN↔VI cho batch 801-900 theo rule batch 06; chỉ xuất patch cuối, không sửa dataset chính. Có tinh chỉnh thêm 5 mục ngữ nghĩa/unit chắc chắn (hoa hồi: cánh→cái; lòng đỏ: unit lòng đỏ→quả)."
}